{
  "symbols": [
    {
      "symbol": "MEMEUSDT",
      "last_price": 0.000627,
      "bid_price": 0.000626,
      "ask_price": 0.000627,
      "quote_volume_24h": 5751527.84,
      "ret_24h": 12.17,
      "trade_count_24h": 73049,
      "ret_5m": 1.4,
      "ret_15m": 3.8,
      "ret_1h": 7.6,
      "quote_volume_5m": 820000.0,
      "quote_volume_15m": 1850000.0,
      "quote_volume_1h": 4200000.0,
      "volume_multiple_5m": 7.4,
      "volume_multiple_15m": 5.8,
      "trade_count_5m": 2150,
      "trade_count_15m": 7600,
      "trade_count_1h": 26400,
      "trade_count_multiple_5m": 4.8,
      "spread_pct": 0.16,
      "depth_usd_1pct_bid": 148000.0,
      "depth_usd_1pct_ask": 136000.0,
      "depth_usd_2pct_bid": 286000.0,
      "depth_usd_2pct_ask": 302000.0,
      "distance_from_24h_high_pct": 7.8,
      "distance_from_30m_high_pct": 1.9,
      "breakout_active": true,
      "held_breakout_retest": true,
      "higher_low_confirmed": true,
      "vwap_reclaim": true,
      "extended_move_flag": false,
      "catalyst_score_override": 8.0,
      "social_score_override": 6.0,
      "circulating_ratio": 0.54,
      "fdv_to_market_cap": 1.6,
      "unlock_within_30d": false,
      "market_flags": [],
      "tags": ["binance-spot", "small-cap-proxy", "top-gainer", "meme-sector"],
      "notes": ["real Binance spot pair; demo scanner snapshot"]
    },
    {
      "symbol": "ORDIUSDT",
      "last_price": 3.423,
      "bid_price": 3.423,
      "ask_price": 3.424,
      "quote_volume_24h": 2294803.75,
      "ret_24h": 3.45,
      "trade_count_24h": 31958,
      "ret_5m": 0.6,
      "ret_15m": 1.7,
      "ret_1h": 4.1,
      "quote_volume_5m": 210000.0,
      "quote_volume_15m": 620000.0,
      "quote_volume_1h": 1520000.0,
      "volume_multiple_5m": 4.2,
      "volume_multiple_15m": 3.6,
      "trade_count_5m": 780,
      "trade_count_15m": 2480,
      "trade_count_1h": 9400,
      "trade_count_multiple_5m": 2.9,
      "spread_pct": 0.03,
      "depth_usd_1pct_bid": 420000.0,
      "depth_usd_1pct_ask": 398000.0,
      "depth_usd_2pct_bid": 850000.0,
      "depth_usd_2pct_ask": 910000.0,
      "distance_from_24h_high_pct": 0.8,
      "distance_from_30m_high_pct": 0.4,
      "breakout_active": false,
      "held_breakout_retest": true,
      "higher_low_confirmed": true,
      "vwap_reclaim": true,
      "extended_move_flag": false,
      "catalyst_score_override": 7.0,
      "social_score_override": 3.0,
      "circulating_ratio": 0.66,
      "fdv_to_market_cap": 1.2,
      "unlock_within_30d": false,
      "market_flags": [],
      "tags": ["binance-spot", "high-beta-alt", "top-gainer", "bitcoin-ecosystem"],
      "notes": ["real Binance spot pair; demo scanner snapshot"]
    },
    {
      "symbol": "WIFUSDT",
      "last_price": 0.1651,
      "bid_price": 0.1651,
      "ask_price": 0.1652,
      "quote_volume_24h": 954498.79,
      "ret_24h": 2.99,
      "trade_count_24h": 42470,
      "ret_5m": 0.3,
      "ret_15m": 1.2,
      "ret_1h": 3.2,
      "quote_volume_5m": 98000.0,
      "quote_volume_15m": 318000.0,
      "quote_volume_1h": 710000.0,
      "volume_multiple_5m": 3.8,
      "volume_multiple_15m": 3.2,
      "trade_count_5m": 940,
      "trade_count_15m": 3100,
      "trade_count_1h": 12400,
      "trade_count_multiple_5m": 2.7,
      "spread_pct": 0.06,
      "depth_usd_1pct_bid": 188000.0,
      "depth_usd_1pct_ask": 172000.0,
      "depth_usd_2pct_bid": 420000.0,
      "depth_usd_2pct_ask": 397000.0,
      "distance_from_24h_high_pct": 0.9,
      "distance_from_30m_high_pct": 0.6,
      "breakout_active": true,
      "held_breakout_retest": false,
      "higher_low_confirmed": true,
      "vwap_reclaim": true,
      "extended_move_flag": false,
      "catalyst_score_override": 5.0,
      "social_score_override": 7.0,
      "circulating_ratio": 0.82,
      "fdv_to_market_cap": 1.0,
      "unlock_within_30d": false,
      "market_flags": [],
      "tags": ["binance-spot", "small-cap-proxy", "top-gainer", "meme-sector"],
      "notes": ["real Binance spot pair; demo scanner snapshot"]
    },
    {
      "symbol": "BONKUSDT",
      "last_price": 0.00000463,
      "bid_price": 0.00000463,
      "ask_price": 0.00000464,
      "quote_volume_24h": 3261489.89,
      "ret_24h": 2.66,
      "trade_count_24h": 23001,
      "ret_5m": 0.2,
      "ret_15m": 0.9,
      "ret_1h": 2.5,
      "quote_volume_5m": 220000.0,
      "quote_volume_15m": 710000.0,
      "quote_volume_1h": 1800000.0,
      "volume_multiple_5m": 2.8,
      "volume_multiple_15m": 2.5,
      "trade_count_5m": 520,
      "trade_count_15m": 1560,
      "trade_count_1h": 6400,
      "trade_count_multiple_5m": 1.9,
      "spread_pct": 0.22,
      "depth_usd_1pct_bid": 96000.0,
      "depth_usd_1pct_ask": 84000.0,
      "depth_usd_2pct_bid": 202000.0,
      "depth_usd_2pct_ask": 224000.0,
      "distance_from_24h_high_pct": 1.7,
      "distance_from_30m_high_pct": 0.9,
      "breakout_active": false,
      "held_breakout_retest": false,
      "higher_low_confirmed": true,
      "vwap_reclaim": false,
      "extended_move_flag": false,
      "catalyst_score_override": 4.0,
      "social_score_override": 6.0,
      "circulating_ratio": 0.74,
      "fdv_to_market_cap": 1.2,
      "unlock_within_30d": false,
      "market_flags": [],
      "tags": ["binance-spot", "small-cap-proxy", "top-gainer", "meme-sector"],
      "notes": ["real Binance spot pair; demo scanner snapshot"]
    },
    {
      "symbol": "PEPEUSDT",
      "last_price": 0.00000291,
      "bid_price": 0.0000029,
      "ask_price": 0.00000291,
      "quote_volume_24h": 18564130.06,
      "ret_24h": 2.11,
      "trade_count_24h": 45329,
      "ret_5m": -0.2,
      "ret_15m": 0.4,
      "ret_1h": 1.8,
      "quote_volume_5m": 780000.0,
      "quote_volume_15m": 2300000.0,
      "quote_volume_1h": 6900000.0,
      "volume_multiple_5m": 2.2,
      "volume_multiple_15m": 2.0,
      "trade_count_5m": 980,
      "trade_count_15m": 3100,
      "trade_count_1h": 11800,
      "trade_count_multiple_5m": 1.6,
      "spread_pct": 0.34,
      "depth_usd_1pct_bid": 740000.0,
      "depth_usd_1pct_ask": 690000.0,
      "depth_usd_2pct_bid": 1500000.0,
      "depth_usd_2pct_ask": 1420000.0,
      "distance_from_24h_high_pct": 1.0,
      "distance_from_30m_high_pct": 0.8,
      "breakout_active": false,
      "held_breakout_retest": false,
      "higher_low_confirmed": false,
      "vwap_reclaim": true,
      "extended_move_flag": false,
      "catalyst_score_override": 3.0,
      "social_score_override": 8.0,
      "circulating_ratio": 0.88,
      "fdv_to_market_cap": 1.0,
      "unlock_within_30d": false,
      "market_flags": ["wide_spread"],
      "tags": ["binance-spot", "high-volume-meme", "top-gainer"],
      "notes": ["real Binance spot pair; demo scanner snapshot"]
    },
    {
      "symbol": "FLOKIUSDT",
      "last_price": 0.00002567,
      "bid_price": 0.00002566,
      "ask_price": 0.00002567,
      "quote_volume_24h": 885416.77,
      "ret_24h": 1.95,
      "trade_count_24h": 70098,
      "ret_5m": -0.4,
      "ret_15m": 0.2,
      "ret_1h": 1.1,
      "quote_volume_5m": 52000.0,
      "quote_volume_15m": 176000.0,
      "quote_volume_1h": 530000.0,
      "volume_multiple_5m": 1.5,
      "volume_multiple_15m": 1.7,
      "trade_count_5m": 620,
      "trade_count_15m": 2200,
      "trade_count_1h": 8800,
      "trade_count_multiple_5m": 1.3,
      "spread_pct": 0.04,
      "depth_usd_1pct_bid": 112000.0,
      "depth_usd_1pct_ask": 104000.0,
      "depth_usd_2pct_bid": 238000.0,
      "depth_usd_2pct_ask": 246000.0,
      "distance_from_24h_high_pct": 0.3,
      "distance_from_30m_high_pct": 0.5,
      "breakout_active": false,
      "held_breakout_retest": false,
      "higher_low_confirmed": false,
      "vwap_reclaim": false,
      "extended_move_flag": false,
      "catalyst_score_override": 2.0,
      "social_score_override": 5.0,
      "circulating_ratio": 0.71,
      "fdv_to_market_cap": 1.3,
      "unlock_within_30d": false,
      "market_flags": [],
      "tags": ["binance-spot", "small-cap-proxy", "top-gainer", "meme-sector"],
      "notes": ["real Binance spot pair; demo scanner snapshot"]
    }
  ]
}
